cities_light/__init__.py
cities_light/abstract_models.py
cities_light/admin.py
cities_light/apps.py
cities_light/downloader.py
cities_light/exceptions.py
cities_light/forms.py
cities_light/geonames.py
cities_light/loading.py
cities_light/models.py
cities_light/receivers.py
cities_light/settings.py
cities_light/signals.py
cities_light/validators.py
cities_light/version.py
cities_light/contrib/__init__.py
cities_light/contrib/ajax_selects_lookups.py
cities_light/contrib/restframework3.py
cities_light/graphql/__init__.py
cities_light/graphql/types.py
cities_light/management/__init__.py
cities_light/management/commands/__init__.py
cities_light/management/commands/cities_light.py
cities_light/management/commands/cities_light_fixtures.py
cities_light/migrations/0001_initial.py
cities_light/migrations/0002_city.py
cities_light/migrations/0003_auto_20141120_0342.py
cities_light/migrations/0004_autoslug_update.py
cities_light/migrations/0005_blank_phone.py
cities_light/migrations/0006_compensate_for_0003_bytestring_bug.py
cities_light/migrations/0007_make_country_name_not_unique.py
cities_light/migrations/0008_city_timezone.py
cities_light/migrations/0009_add_subregion.py
cities_light/migrations/0010_auto_20200508_1851.py
cities_light/migrations/0011_alter_city_country_alter_city_region_and_more.py
cities_light/migrations/__init__.py
cities_light/tests/__init__.py
cities_light/tests/base.py
cities_light/tests/models.py
cities_light/tests/test_contrib.py
cities_light/tests/test_downloader.py
cities_light/tests/test_fixtures.py
cities_light/tests/test_form.py
cities_light/tests/test_import.py
cities_light/tests/test_migrations.py
cities_light/tests/test_models.py
cities_light/tests/test_unicode.py
cities_light/tests/test_update.py
cities_light/tests/fixtures/import/angouleme.json
cities_light/tests/fixtures/import/angouleme_city.txt
cities_light/tests/fixtures/import/angouleme_city_wtz.txt
cities_light/tests/fixtures/import/angouleme_country.txt
django_cities_light-3.10.1.dist-info/AUTHORS
django_cities_light-3.10.1.dist-info/LICENSE
django_cities_light-3.10.1.dist-info/METADATA
django_cities_light-3.10.1.dist-info/WHEEL
django_cities_light-3.10.1.dist-info/top_level.txt
django_cities_light-3.10.1.dist-info/RECORD
