Metadata-Version: 2.1
Name: django-cities-light
Version: 3.10.1
Summary: Simple alternative to django-cities
Home-page: https://github.com/yourlabs/django-cities-light
Author: James Pic,Dominick Rivard,Alexey Evseev
Author-email: jamespic@gmail.com, dominick.rivard@gmail.com, myhappydo@gmail.com
License: MIT
Keywords: django cities countries postal codes
Classifier: Development Status :: 5 - Production/Stable
Classifier: Environment :: Web Environment
Classifier: Intended Audience :: Developers
Classifier: License :: OSI Approved :: MIT License
Classifier: Operating System :: OS Independent
Classifier: Framework :: Django
Classifier: Framework :: Django :: 3.2
Classifier: Framework :: Django :: 4.0
Classifier: Framework :: Django :: 4.1
Classifier: Framework :: Django :: 4.2
Classifier: Programming Language :: Python
Classifier: Programming Language :: Python :: 3
Classifier: Programming Language :: Python :: 3.8
Classifier: Programming Language :: Python :: 3.9
Classifier: Programming Language :: Python :: 3.10
Classifier: Programming Language :: Python :: 3.11
Classifier: Programming Language :: Python :: 3.12
Classifier: Topic :: Internet :: WWW/HTTP
Classifier: Topic :: Software Development :: Libraries :: Python Modules
License-File: LICENSE
License-File: AUTHORS
Requires-Dist: pytz
Requires-Dist: unidecode>=0.04.13
Requires-Dist: django-autoslug>=1.9.8
Requires-Dist: progressbar2>=3.51.4
